muretech/__init__.py
muretech/authentication/__init__.py
muretech/organizations/__init__.py
muretech/solutions/__init__.py
muretech_python-0.0.1.dist-info/LICENSE
muretech_python-0.0.1.dist-info/METADATA
muretech_python-0.0.1.dist-info/WHEEL
muretech_python-0.0.1.dist-info/RECORD
